pymovies/__init__.py
pymovies/__main__.py
pymovies/list_movies.py
pymovies/quote_from_category.py
pymovies/quote_of_the_day.py
pymovies/quotes.py
pymovies/random_quote.py
pymovies-0.1.1.dist-info/LICENSE
pymovies-0.1.1.dist-info/METADATA
pymovies-0.1.1.dist-info/WHEEL
pymovies-0.1.1.dist-info/top_level.txt
pymovies-0.1.1.dist-info/RECORD
