Metadata-Version: 2.1
Name: pymovies
Version: 0.1.1
Summary: An app where users can get random quotes and browse quotes by different categories or movies.
Author-email: May Zhou <zz4206@nyu.edu>, Fatima Villena <fav2019@nyu.edu>, Sandy Li <rl4385@nyu.edu>, Safia Billah <ssb9872@nyu.edu>
License: GNU GENERAL PUBLIC LICENSE
Project-URL: homepage, https://github.com/software-students-fall2024/3-python-package-three
Project-URL: repository, https://github.com/software-students-fall2024/3-python-package-three.git
Project-URL: bug_tracker, https://github.com/software-students-fall2024/3-python-package-three/issues
Keywords: python,package,build,quotes
Classifier: Programming Language :: Python :: 3
Classifier: Intended Audience :: End Users/Desktop
Classifier: License :: OSI Approved :: GNU General Public License v3 (GPLv3)
Classifier: Operating System :: OS Independent
Requires-Python: >=3.7
License-File: LICENSE
Provides-Extra: dev
Requires-Dist: pytest; extra == "dev"
